pyplater_cli/__init__.py
pyplater_cli/groups/__init__.py
pyplater_cli/groups/base.py
pyplater_cli/groups/delete.py
pyplater_cli/groups/edit.py
pyplater_cli/groups/git.py
pyplater_cli/groups/insert.py
pyplater_cli/groups/save.py
pyplater_cli/groups/view.py
pyplater_cli/main.py
pyplater_cli/pyplater-templates/snippets/sqlalchemy/db/crud.py
pyplater_cli/pyplater-templates/snippets/sqlalchemy/db/database.py
pyplater_cli/pyplater-templates/snippets/sqlalchemy/db/model.py
pyplater_cli/pyplater-templates/snippets/sqlalchemy/db/schema.py
pyplater_cli/pyplater-templates/templates/starter/cookiecutter.json
pyplater_cli/pyplater-templates/templates/starter/{{cookiecutter.project_slug}}/.env.example
pyplater_cli/pyplater-templates/templates/starter/{{cookiecutter.project_slug}}/.flake8
pyplater_cli/pyplater-templates/templates/starter/{{cookiecutter.project_slug}}/.gitignore
pyplater_cli/pyplater-templates/templates/starter/{{cookiecutter.project_slug}}/README.md
pyplater_cli/pyplater-templates/templates/starter/{{cookiecutter.project_slug}}/pyproject.toml
pyplater_cli/pyplater-templates/templates/starter/{{cookiecutter.project_slug}}/tests/__init__.py
pyplater_cli/pyplater-templates/templates/starter/{{cookiecutter.project_slug}}/tests/test_project.py
pyplater_cli/pyplater-templates/templates/starter/{{cookiecutter.project_slug}}/{{cookiecutter.project_slug}}/__init__.py
pyplater_cli/pyplater-templates/templates/starter/{{cookiecutter.project_slug}}/{{cookiecutter.project_slug}}/config.py
pyplater_cli/pyplater-templates/templates/starter/{{cookiecutter.project_slug}}/{{cookiecutter.project_slug}}/main.py
pyplater_cli/tests/__init__.py
pyplater_cli/tests/test_base.py
pyplater_cli/tests/test_delete.py
pyplater_cli/tests/test_edit.py
pyplater_cli/tests/test_git.py
pyplater_cli/tests/test_insert.py
pyplater_cli/tests/test_questionary.py
pyplater_cli/tests/test_save.py
pyplater_cli/tests/test_tree.py
pyplater_cli/tests/test_view.py
pyplater_cli/utils/__init__.py
pyplater_cli-1.0.0.dist-info/LICENSE.md
pyplater_cli-1.0.0.dist-info/METADATA
pyplater_cli-1.0.0.dist-info/WHEEL
pyplater_cli-1.0.0.dist-info/entry_points.txt
pyplater_cli-1.0.0.dist-info/RECORD
