Metadata-Version: 2.1
Name: pyplater-cli
Version: 1.0.0
Summary: Create Python Script CLI
License: MIT
Author: David Rose-Franklin
Author-email: david.rosefranklin96@gmail.com
Requires-Python: >=3.10,<4.0
Classifier: Development Status :: 3 - Alpha
Classifier: Intended Audience :: Developers
Classifier: License :: OSI Approved :: MIT License
Classifier: Operating System :: Microsoft :: Windows
Classifier: Programming Language :: Python :: 3
Classifier: Programming Language :: Python :: 3.10
Classifier: Programming Language :: Python :: 3.11
Requires-Dist: click (>=8.1.5,<9.0.0)
Requires-Dist: cookiecutter (>=2.2.3,<3.0.0)
Requires-Dist: questionary (>=1.10.0,<2.0.0)
Requires-Dist: requests (>=2.31.0,<3.0.0)
Requires-Dist: toml (>=0.10.2,<0.11.0)
